outputfile-1.3.2.dist-info/METADATA
outputfile-1.3.2.dist-info/WHEEL
outputfile-1.3.2.dist-info/entry_points.txt
outputfile-1.3.2.dist-info/licenses/LICENSE
outputfile/__init__.py
outputfile-1.3.2.dist-info/RECORD
