Metadata-Version: 2.1
Name: outputfile
Version: 1.3.2
Summary: Timestamp Preserving Output File Writer
Classifier: Programming Language :: Python :: 3
Classifier: Operating System :: OS Independent
Project-URL: Homepage, https://github.com/nbiotcloud/outputfile
Project-URL: Documentation, https://outputfile.readthedocs.io/en/stable/
Project-URL: Bug Tracker, https://github.com/nbiotcloud/outputfile/issues
Requires-Python: <4.0,>=3.10.0
Requires-Dist: mkdocstrings<1.0.0
